{
  "metadata": {
    "label": "animoca_brands",
    "category": "fund",
    "subcategory": "",
    "website": "https://www.animocabrands.com",
    "description": "",
    "organization": "animoca_brands"
  },
  "addresses": [
    {
      "address": "Ef--iZr4o1zvFU9u0Gc30Sk2dNzWJTk8ERr5xgv-AOHBjz55",
      "source": "",
      "comment": "Animoca Brands Pool 1",
      "tags": [
        "validator"
      ],
      "submittedBy": "Lucky0041",
      "submissionTimestamp": "2025-09-29T00:00:01Z"
    },
    {
      "address": "Ef8hpW8uv5Ngz5m5nV_tSRBfo_VSmHz6pw_JQ6Y_PXV5Qxqt",
      "source": "",
      "comment": "Animoca Brands Pool 2",
      "tags": [
        "validator"
      ],
      "submittedBy": "Lucky0041",
      "submissionTimestamp": "2025-09-29T00:00:01Z"
    }
  ]
}
