{
    "metadata": {
        "label": "bigone",
        "category": "CEX",
        "subcategory": "",
        "website": "https://big.one",
        "description": "",
        "organization": "bigone"
    },
    "addresses": [
        {
            "address": "EQCaWCwjJmuOpH63ERijwEDUKyMLImb-z_4tPNOQwJIsNcZW",
            "source": "datalake-test.cex_labels_20241116",
            "comment": "",
            "tags": [],
            "submittedBy": "ziga",
            "submissionTimestamp": "2024-12-12T10:09:26Z"
        }
    ]
}