{
    "metadata": {
        "label": "bitfinex",
        "category": "CEX",
        "subcategory": "",
        "website": "https://bitfinex.com",
        "description": "",
        "organization": "bitfinex"
    },
    "addresses": [
        {
            "address": "EQBqWnahU4z5WWWQ7DcIRwZJw0JiS_kuY6anoVJU7e2pBBuP",
            "source": "https://tonalytica.redoubt.online/queries/776/source",
            "comment": "",
            "tags": [],
            "submittedBy": "ziga",
            "submissionTimestamp": "2024-11-25T19:52:44Z"
        },
        {
            "address": "EQBBlxK8VBxEidbxw4oQVyLSk7iEf9VPJxetaRQpEbi-XG4U",
            "source": "https://intel.arkm.com/explorer/address/0:419712BC541C4489D6F1C38A105722D293B8847FD54F2717AD69142911B8BE5C",
            "comment": "",
            "tags": [],
            "submittedBy": "Lucky0041",
            "submissionTimestamp": "2025-08-21T19:52:44Z"
        }
    ]
}
