{
    "metadata": {
        "label": "parik24",
        "category": "gaming",
        "subcategory": "gambling",
        "website": "https://parik24.pro",
        "description": "",
        "organization": "parik24"
    },
    "addresses": [
        {
            "address": "EQAigd8MjqsJejMuIB0UPhErOlGe22dezkpjvpWt9kOrtkG8",
            "source": "",
            "comment": "",
            "tags": [],
            "submittedBy": "Lucky0041",
            "submissionTimestamp": "2025-09-08T00:00:01Z"
        }
    ]
}
