{
    "metadata": {
        "label": "stars_birds",
        "category": "gaming",
        "subcategory": "",
        "website": "https://t.me/StarsBirdsBot",
        "description": "",
        "organization": "stars_birds"
    },
    "addresses": [
        {
            "address": "EQAYKVbgMenHc4c87UqaVkeF8B9-XwST-341qYCCDcpbCVfy",
            "source": "https://t.me/StarsBirdsPayouts",
            "comment": "",
            "tags": [],
            "submittedBy": "Lucky0041",
            "submissionTimestamp": "2026-03-03T00:00:01Z"
        }
    ]
}
