{
    "metadata": {
        "label": "xstar_fleet",
        "category": "gaming",
        "subcategory": "",
        "website": "https://t.me/XStarFleet_bot",
        "description": "",
        "organization": "xstar_fleet"
    },
    "addresses": [
        {
            "address": "EQBtVd55UGT2ppYwa9_ks5DHJkAjaohoIX91u2fZxJOpEJRN",
            "source": "",
            "comment": "",
            "tags": [],
            "submittedBy": "ohld",
            "submissionTimestamp": "2025-02-10T00:00:01Z"
        },
        {
            "address": "EQBtjRZMFl2qvEtvZI9T4R9g5P7HGLQp-PYPGPZBDsC5kCqT",
            "source": "",
            "comment": "",
            "tags": [],
            "submittedBy": "ohld",
            "submissionTimestamp": "2025-02-10T00:00:01Z"
        }
    ]
}