{
    "metadata": {
        "label": "sybil_EQBoCCr",
        "category": "scripted-activity",
        "subcategory": "sybil",
        "website": "",
        "description": "",
        "organization": "sybil_EQBoCCr"
    },
    "addresses": [
        {
            "address": "EQBoCCrm-_i9Id1eKAsGHPB28FsDCYusC91Xuc2x47LoyIjZ",
            "source": "",
            "comment": "",
            "tags": [],
            "submittedBy": "Lucky0041",
            "submissionTimestamp": "2025-06-03T00:00:00Z"
         }
    ]
}
